{
  "server":"23.95.242.204",
  "server_port":25,
  "local_address": "127.0.0.1",
  "local_port":1080,
  "password":"huzhipeng0826",
  "timeout":300,
  "method":"aes-256-cfb",
  "fast_open": false
}


//0.购买服务器
//https://billing.virmach.com/cart.php?gid=1
//安装python pip
//1. wget https://bootstrap.pypa.io/get-pip.py --no-check-certificate
//2.python3 get-pip.py
//安装ss
//3.pip install shadowsocks
//配置ss
//4.vi /etc/shadowsocks.json
//server为自己购买的ip地址
//{
//"server":107.174.203.115”,
//"server_port":25,
//"local_address": "127.0.0.1",
//"local_port":1080,
//"password”:”hello2019”,
//"timeout":300,
//"method":"aes-256-cfb",
//"fast_open": false
//}
//后台启动ss
//5.ssserver -c /etc/shadowsocks.json -d start